ip_stack_sdk-1.0.0.dist-info/licenses/LICENSE
ipstack/__init__.py
ipstack/api_helper.py
ipstack/configuration.py
ipstack/ipstack_client.py
ipstack/controllers/__init__.py
ipstack/controllers/base_controller.py
ipstack/controllers/bulk_ip_lookup_controller.py
ipstack/controllers/requester_ip_lookup_controller.py
ipstack/controllers/standard_ip_lookup_controller.py
ipstack/exceptions/__init__.py
ipstack/exceptions/api_exception.py
ipstack/http/__init__.py
ipstack/http/http_call_back.py
ipstack/http/http_method_enum.py
ipstack/http/http_request.py
ipstack/http/http_response.py
ipstack/http/auth/__init__.py
ipstack/http/auth/custom_query_authentication.py
ipstack/models/__init__.py
ipstack/models/batch.py
ipstack/models/connection.py
ipstack/models/connection_3.py
ipstack/models/currency.py
ipstack/models/currency_3.py
ipstack/models/error.py
ipstack/models/language.py
ipstack/models/languages.py
ipstack/models/languages_1.py
ipstack/models/location.py
ipstack/models/location_3.py
ipstack/models/location_4.py
ipstack/models/m_101_invalid_access_key.py
ipstack/models/m_200_ok_basic_standard_ip_lookup.py
ipstack/models/m_200_ok_bulk_ip_lookup.py
ipstack/models/m_200_ok_hostname.py
ipstack/models/m_200_ok_hostname_1.py
ipstack/models/m_200_ok_requester_ip_lookup.py
ipstack/models/m_200_ok_response_in_different_language.py
ipstack/models/m_200_ok_response_in_different_language_copy.py
ipstack/models/m_200_ok_specific_response_with_fields_parameter.py
ipstack/models/m_200_ok_specific_response_with_fields_parameter_1.py
ipstack/models/result.py
ipstack/models/result_1.py
ipstack/models/time_zone.py
ipstack/models/time_zone_3.py
ipstack/models/time_zone_7.py
ipstack/utilities/__init__.py
ipstack/utilities/file_wrapper.py
ipstack/utilities/xml_utilities.py
ip_stack_sdk-1.0.0.dist-info/METADATA
ip_stack_sdk-1.0.0.dist-info/WHEEL
ip_stack_sdk-1.0.0.dist-info/top_level.txt
ip_stack_sdk-1.0.0.dist-info/RECORD
