Metadata-Version: 2.4
Name: ip-stack-sdk
Version: 1.0.0
Summary: IPstack API is a comprehensive IP geolocation service that provides detailed location information for IPv4 and IPv6 addresses, including country, city, coordinates, timezone, currency, and ISP data. The API offers three main endpoints: Standard IP Lookup for single addresses, Bulk IP Lookup for multiple addresses, and Requester IP Lookup to detect the requesting IP address, with support for multiple languages and output formats
Author-email: Muhammad Hamza Shahzad <muhammad.hamza@apimatic.io>
Project-URL: Documentation, https://docs.apimatic.io/
Requires-Python: >=3.7
License-File: LICENSE
Requires-Dist: apimatic-core>=0.2.20,~=0.2.0
Requires-Dist: apimatic-core-interfaces>=0.1.5,~=0.1.0
Requires-Dist: apimatic-requests-client-adapter>=0.1.6,~=0.1.0
Provides-Extra: testutils
Requires-Dist: pytest>=7.2.2; extra == "testutils"
Dynamic: license-file
